flake8_raise.py
flake8_raise-0.0.5.dist-info/LICENSE
flake8_raise-0.0.5.dist-info/METADATA
flake8_raise-0.0.5.dist-info/WHEEL
flake8_raise-0.0.5.dist-info/entry_points.txt
flake8_raise-0.0.5.dist-info/top_level.txt
flake8_raise-0.0.5.dist-info/RECORD
