Metadata-Version: 2.1
Name: flake8-raise
Version: 0.0.5
Summary: A flake8 plugin that finds that finds improvements for raise statements.
Home-page: https://github.com/jdufresne/flake8-raise
Author: Jon Dufresne
Author-email: jon.dufresne@gmail.com
License: MIT
Platform: UNKNOWN
Classifier: Development Status :: 2 - Pre-Alpha
Classifier: Framework :: Flake8
Classifier: Intended Audience :: Developers
Classifier: License :: OSI Approved :: MIT License
Classifier: Programming Language :: Python :: 3
Classifier: Programming Language :: Python :: 3 :: Only
Classifier: Programming Language :: Python :: 3.5
Classifier: Programming Language :: Python :: 3.6
Classifier: Programming Language :: Python :: 3.7
Classifier: Programming Language :: Python :: 3.8
Classifier: Programming Language :: Python :: Implementation :: CPython
Classifier: Programming Language :: Python :: Implementation :: PyPy
Requires-Python: >=3.5
Requires-Dist: flake8 (>=3.2.0)
Requires-Dist: importlib-metadata (>=0.9) ; python_version < "3.8"
